[
  {
    "Name": "GIKI",
    "Degree": "Bachelors, Masters",
    "Campus": "Topi, Khyber Pakhtunkhwa"
  },
  {
    "Name": "Virtual University of Pakistan",
    "Degree": "Bachelors, Masters",
    "Campus": "Virtual"
  },
  {
    "Name": "University of Lahore",
    "Degree": "Bachelors, Masters",
    "Campus": "Lahore"
  },
  {
    "Name": "University of Central Punjab",
    "Degree": "Bachelors, Masters",
    "Campus": "Lahore"
  },
  {
    "Name": "Arid Agriculture University",
    "Degree": "Bachelors, Masters",
    "Campus": "Islamabad, Faisalabad, Sahiwal"
  },
  {
    "Name": "University of Agriculture",
    "Degree": "Bachelors, Masters",
    "Campus": "Faisalabad"
  },
  {
    "Name": "Balochistan University of Information Technology, Engineering and Management Sciences",
    "Degree": "Bachelors, Masters",
    "Campus": "Balochistan"
  },
  {
    "Name": "Sir Syed University of Engineering & Technology",
    "Degree": "Bachelors, Masters",
    "Campus": "Karachi"
  },
  {
    "Name": "Preston University",
    "Degree": "Bachelors, Masters",
    "Campus": "Islamabad, Karachi"
  },
  {
    "Name": "Pakistan Institute of Engineering & Applied Sciences (PIEAS)",
    "Degree": "Bachelors, Masters",
    "Campus": "Islamabad"
  },
  {
    "Name": "NED (University of Engeenering and Technology)",
    "Degree": "Bachelors, Masters",
    "Campus": "Karachi"
  },
  {
    "Name": "NUST",
    "Degree": "Bachelors, Masters",
    "Campus": "Islamabad"
  },
  {
    "Name": "National Textile University",
    "Degree": "Bachelors, Masters",
    "Campus": "Faisalabad, Karachi"
  },
  {
    "Name": "Mehran University of Engineering & Technology",
    "Degree": "Bachelors, Masters",
    "Campus": "Jamshoro"
  },
  {
    "Name": "LUMS",
    "Degree": "Bachelors, Masters, Phd",
    "Campus": "Lahore"
  },
  {
    "Name": "Lahore College for Women University",
    "Degree": "Bachelors, Masters",
    "Campus": "Lahore"
  },
  {
    "Name": "Jinnah University for Women",
    "Degree": "Bachelors, Masters",
    "Campus": "Karachi"
  },
  {
    "Name": "Islamia College University",
    "Degree": "Bachelors, Masters",
    "Campus": "Peshawar"
  },
  {
    "Name": "Iqra University",
    "Degree": "Bachelors, Masters",
    "Campus": "Karachi"
  },
  {
    "Name": "FAST NUCES",
    "Degree": "Bachelors, Masters, Phd",
    "Campus": "Islamabad, Peshawar, Lahore, Karachi"
  },
  {
    "Name": "COMSATS ",
    "Degree": "Bachelors, Masters, Phd",
    "Campus": "Islamabad, Abbottabad, Lahore, Wah, Attock, Sahiwal, Vehari, Virtual"
  },
  {
    "Name": "City University of Science & Information Technology",
    "Degree": "Bachelors, Masters",
    "Campus": "Peshawar"
  },
  {
    "Name": "Beaconhouse National University",
    "Degree": "Bachelors, Masters",
    "Campus": "Lahore"
  },
  {
    "Name": "Bahauddin Zakariya University",
    "Degree": "Bachelors, Masters",
    "Campus": "Multan"
  },
  {
    "Name": "Bacha Khan University",
    "Degree": "Bachelors, Masters",
    "Campus": "Khyber Pakhtunkhwa"
  },
  {
    "Name": "Allama Iqbal Open University",
    "Degree": "Bachelors, Masters",
    "Campus": "Islamabad"
  },
  {
    "Name": "Abbottabad University of Science and Technology (AUST)",
    "Degree": "Bachelors, Masters",
    "Campus": "Abbottabad"
  }
]